Workbook

Sheet 🏠 Start Here
A1: 📈 OPTIONS 'BREAKOUT' PLAYBOOK — Bull Call Spread Trade Journal
A2: PRICE Framework Trade Journal | For Educational Purposes Only
A5: ◈ HOW TO USE THIS JOURNAL
B6: Step 1: | C6: Go to the '📓 Trade Journal' sheet
B7: Step 2: | C7: Fill in ONE row per Bull Call Spread trade — BEFORE you place the order
B8: Step 3: | C8: Tick all 5 PRICE checklist boxes (columns N–R) — only trade if ALL 5 are ✔
B9: Step 4: | C9: Verify: Is breakeven BELOW current support? Is IV Rank < 50?
B10: Step 5: | C10: Log your Exit Date, Exit Price, and P&L when you close the position
B11: Step 6: | C11: Review your '📊 Performance' dashboard weekly to spot patterns
A13: ✦ SHEETS IN THIS WORKBOOK
B14: 🏠 Start Here | C14: → You are here! Read instructions before trading.
B15: 📓 Trade Journal | C15: → Log every Bull Call Spread trade here. One row per trade.
B16: 📊 Performance | C16: → Auto-calculated win rate, P&L, R:R, PRICE compliance score.
B17: 📚 PRICE Cheatsheet | C17: → Full 5-step execution framework + Entry/Exit trigger table.
A19: ⚡ THE PRICE EXECUTION FRAMEWORK — 5 STEPS
B20: P | C20: PICK Expiration: Target 30–45 DTE. Minimum 16 DTE. Avoid earnings ±7 days.
B21: R | C21: REVIEW Strike: Long call ATM–slightly OTM (Delta 0.40–0.55). Short call at resistance or EM upper bound.
B22: I | C22: INSPECT Liquidity: Bid-ask spread < $0.20 per leg. Open Interest > 100 contracts per leg.
B23: C | C23: CONDITION Check: EMA21 > EMA50 > EMA200 on daily chart. IV Rank < 50. Near 52-week high breakout.
B24: E | C24: EXECUTE Mid-Price: Place LIMIT order at mid-price. Never chase the ask. Set 50% profit target GTC immediately.
A26: 🎨 COLOUR CODING GUIDE
B27: Green background = Trade closed at PROFIT (≥ 50% of max profit)
B28: Red background = Trade closed at LOSS (≥ max loss threshold)
B29: Yellow background = Trade still OPEN
B30: Dark blue header = Required field — fill in BEFORE placing trade
A32: ⚠️ DISCLAIMER
B33: For educational purposes only. Not investment advice. Options trading involves significant risk and is not appropriate for all investors. All examples are hypothetical and illustrative. Past performance is not indicative of future results. Offered through Moomoo Securities Malaysia Sdn. Bhd. (SC Malaysia, CMSL No. eCMSL/A0397/2024) and Moomoo Financial Singapore Pte. Ltd. (MAS, CMS Licence No. CMS101000). Always paper trade before committing real capital.

Sheet 📓 Trade Journal
A1: 📓 BREAKOUT PLAYBOOK — Bull Call Spread Trade Journal
A2: # | B2: Entry Date | C2: Ticker | D2: Strategy | E2: Long Strike | F2: Short Strike | G2: Expiry Date | H2: DTE at Entry | I2: Long Prem ($) | J2: Short Prem ($) | K2: Net Debit ($) | L2: Contracts | M2: Total Cost ($) | N2: P — Expiry OK? | O2: R — Strike OK? | P2: I — Liquidity OK? | Q2: C — Condition OK? | R2: E — Mid-Price OK? | S2: PRICE Score | T2: Max Loss ($) | U2: Max Profit ($) | V2: Breakeven ($) | W2: Return on Risk | X2: Exit Date | Y2: Exit Price ($) | Z2: Realised P&L ($) | AA2: Result | AB2: Exit Reason | AC2: Notes
A3: 1 | B3: 15-Apr-26 | C3: TSM | D3: Bull Call Spread | E3: 340 | F3: 355 | G3: 01-May-26 | H3: 22 | I3: 8.5 | J3: 3.05 | K3: =I3-J3 -> 5.45 | L3: 1 | M3: =K3*L3*100 -> 545 | N3: ✔ | O3: ✔ | P3: ✔ | Q3: ✔ | R3: ✔ | S3: =COUNTIF(N3:R3,"✔") -> 5 | T3: =M3 -> 545 | U3: =(F3-E3)*100*L3-M3 -> 955 | V3: =E3+K3 -> 345.45 | W3: =IFERROR(U3/T3,"") -> 1.7522936 | AB3: Paper Trade — Webinar Example | AC3: TSM near $372.80 resistance. IV Rank 29. POP 61.57%.
K4: =IFERROR(I4-J4,"") -> 0 | M4: =IFERROR(K4*L4*100,"") -> 0 | S4: =IFERROR(COUNTIF(N4:R4,"✔"),"") -> 0 | T4: =IFERROR(M4,"") -> 0 | U4: =IFERROR((F4-E4)*100*L4-M4,"") -> 0 | V4: =IFERROR(E4+K4,"") -> 0 | W4: =IFERROR(U4/T4,"") | Z4: =IFERROR((Y4-K4)*100*L4,"") -> 0 | AA4: =IFERROR(IF(Z4="","OPEN",IF(Z4>0,"WIN","LOSS")),"") -> LOSS
K5: =IFERROR(I5-J5,"") -> 0 | M5: =IFERROR(K5*L5*100,"") -> 0 | S5: =IFERROR(COUNTIF(N5:R5,"✔"),"") -> 0 | T5: =IFERROR(M5,"") -> 0 | U5: =IFERROR((F5-E5)*100*L5-M5,"") -> 0 | V5: =IFERROR(E5+K5,"") -> 0 | W5: =IFERROR(U5/T5,"") | Z5: =IFERROR((Y5-K5)*100*L5,"") -> 0 | AA5: =IFERROR(IF(Z5="","OPEN",IF(Z5>0,"WIN","LOSS")),"") -> LOSS
K6: =IFERROR(I6-J6,"") -> 0 | M6: =IFERROR(K6*L6*100,"") -> 0 | S6: =IFERROR(COUNTIF(N6:R6,"✔"),"") -> 0 | T6: =IFERROR(M6,"") -> 0 | U6: =IFERROR((F6-E6)*100*L6-M6,"") -> 0 | V6: =IFERROR(E6+K6,"") -> 0 | W6: =IFERROR(U6/T6,"") | Z6: =IFERROR((Y6-K6)*100*L6,"") -> 0 | AA6: =IFERROR(IF(Z6="","OPEN",IF(Z6>0,"WIN","LOSS")),"") -> LOSS
K7: =IFERROR(I7-J7,"") -> 0 | M7: =IFERROR(K7*L7*100,"") -> 0 | S7: =IFERROR(COUNTIF(N7:R7,"✔"),"") -> 0 | T7: =IFERROR(M7,"") -> 0 | U7: =IFERROR((F7-E7)*100*L7-M7,"") -> 0 | V7: =IFERROR(E7+K7,"") -> 0 | W7: =IFERROR(U7/T7,"") | Z7: =IFERROR((Y7-K7)*100*L7,"") -> 0 | AA7: =IFERROR(IF(Z7="","OPEN",IF(Z7>0,"WIN","LOSS")),"") -> LOSS
K8: =IFERROR(I8-J8,"") -> 0 | M8: =IFERROR(K8*L8*100,"") -> 0 | S8: =IFERROR(COUNTIF(N8:R8,"✔"),"") -> 0 | T8: =IFERROR(M8,"") -> 0 | U8: =IFERROR((F8-E8)*100*L8-M8,"") -> 0 | V8: =IFERROR(E8+K8,"") -> 0 | W8: =IFERROR(U8/T8,"") | Z8: =IFERROR((Y8-K8)*100*L8,"") -> 0 | AA8: =IFERROR(IF(Z8="","OPEN",IF(Z8>0,"WIN","LOSS")),"") -> LOSS
K9: =IFERROR(I9-J9,"") -> 0 | M9: =IFERROR(K9*L9*100,"") -> 0 | S9: =IFERROR(COUNTIF(N9:R9,"✔"),"") -> 0 | T9: =IFERROR(M9,"") -> 0 | U9: =IFERROR((F9-E9)*100*L9-M9,"") -> 0 | V9: =IFERROR(E9+K9,"") -> 0 | W9: =IFERROR(U9/T9,"") | Z9: =IFERROR((Y9-K9)*100*L9,"") -> 0 | AA9: =IFERROR(IF(Z9="","OPEN",IF(Z9>0,"WIN","LOSS")),"") -> LOSS
K10: =IFERROR(I10-J10,"") -> 0 | M10: =IFERROR(K10*L10*100,"") -> 0 | S10: =IFERROR(COUNTIF(N10:R10,"✔"),"") -> 0 | T10: =IFERROR(M10,"") -> 0 | U10: =IFERROR((F10-E10)*100*L10-M10,"") -> 0 | V10: =IFERROR(E10+K10,"") -> 0 | W10: =IFERROR(U10/T10,"") | Z10: =IFERROR((Y10-K10)*100*L10,"") -> 0 | AA10: =IFERROR(IF(Z10="","OPEN",IF(Z10>0,"WIN","LOSS")),"") -> LOSS
K11: =IFERROR(I11-J11,"") -> 0 | M11: =IFERROR(K11*L11*100,"") -> 0 | S11: =IFERROR(COUNTIF(N11:R11,"✔"),"") -> 0 | T11: =IFERROR(M11,"") -> 0 | U11: =IFERROR((F11-E11)*100*L11-M11,"") -> 0 | V11: =IFERROR(E11+K11,"") -> 0 | W11: =IFERROR(U11/T11,"") | Z11: =IFERROR((Y11-K11)*100*L11,"") -> 0 | AA11: =IFERROR(IF(Z11="","OPEN",IF(Z11>0,"WIN","LOSS")),"") -> LOSS
K12: =IFERROR(I12-J12,"") -> 0 | M12: =IFERROR(K12*L12*100,"") -> 0 | S12: =IFERROR(COUNTIF(N12:R12,"✔"),"") -> 0 | T12: =IFERROR(M12,"") -> 0 | U12: =IFERROR((F12-E12)*100*L12-M12,"") -> 0 | V12: =IFERROR(E12+K12,"") -> 0 | W12: =IFERROR(U12/T12,"") | Z12: =IFERROR((Y12-K12)*100*L12,"") -> 0 | AA12: =IFERROR(IF(Z12="","OPEN",IF(Z12>0,"WIN","LOSS")),"") -> LOSS
K13: =IFERROR(I13-J13,"") -> 0 | M13: =IFERROR(K13*L13*100,"") -> 0 | S13: =IFERROR(COUNTIF(N13:R13,"✔"),"") -> 0 | T13: =IFERROR(M13,"") -> 0 | U13: =IFERROR((F13-E13)*100*L13-M13,"") -> 0 | V13: =IFERROR(E13+K13,"") -> 0 | W13: =IFERROR(U13/T13,"") | Z13: =IFERROR((Y13-K13)*100*L13,"") -> 0 | AA13: =IFERROR(IF(Z13="","OPEN",IF(Z13>0,"WIN","LOSS")),"") -> LOSS
K14: =IFERROR(I14-J14,"") -> 0 | M14: =IFERROR(K14*L14*100,"") -> 0 | S14: =IFERROR(COUNTIF(N14:R14,"✔"),"") -> 0 | T14: =IFERROR(M14,"") -> 0 | U14: =IFERROR((F14-E14)*100*L14-M14,"") -> 0 | V14: =IFERROR(E14+K14,"") -> 0 | W14: =IFERROR(U14/T14,"") | Z14: =IFERROR((Y14-K14)*100*L14,"") -> 0 | AA14: =IFERROR(IF(Z14="","OPEN",IF(Z14>0,"WIN","LOSS")),"") -> LOSS
K15: =IFERROR(I15-J15,"") -> 0 | M15: =IFERROR(K15*L15*100,"") -> 0 | S15: =IFERROR(COUNTIF(N15:R15,"✔"),"") -> 0 | T15: =IFERROR(M15,"") -> 0 | U15: =IFERROR((F15-E15)*100*L15-M15,"") -> 0 | V15: =IFERROR(E15+K15,"") -> 0 | W15: =IFERROR(U15/T15,"") | Z15: =IFERROR((Y15-K15)*100*L15,"") -> 0 | AA15: =IFERROR(IF(Z15="","OPEN",IF(Z15>0,"WIN","LOSS")),"") -> LOSS
... K52: =IFERROR(I52-J52,"") -> 0 | M52: =IFERROR(K52*L52*100,"") -> 0 | S52: =IFERROR(COUNTIF(N52:R52,"✔"),"") -> 0 | T52: =IFERROR(M52,"") -> 0 | U52: =IFERROR((F52-E52)*100*L52-M52,"") -> 0 | V52: =IFERROR(E52+K52,"") -> 0 | W52: =IFERROR(U52/T52,"") | Z52: =IFERROR((Y52-K52)*100*L52,"") -> 0 | AA52: =IFERROR(IF(Z52="","OPEN",IF(Z52>0,"WIN","LOSS")),"") -> LOSS

Sheet 📊 Performance
A1: 📊 PERFORMANCE DASHBOARD — Bull Call Spread Results
A4: 📈 OVERALL SUMMARY
B5: Total Trades Entered | C5: =COUNTA('📓 Trade Journal'!B3:B52) -> 1
B6: Total Closed (WIN+LOSS) | C6: =COUNTIF('📓 Trade Journal'!AA3:AA52,"WIN")+COUNTIF('📓 Trade Journal'!AA3:AA52,"LOSS") -> 49
B7: Open Positions | C7: =COUNTIF('📓 Trade Journal'!AA3:AA52,"OPEN") -> 0
B8: WIN Count | C8: =COUNTIF('📓 Trade Journal'!AA3:AA52,"WIN") -> 0
B9: LOSS Count | C9: =COUNTIF('📓 Trade Journal'!AA3:AA52,"LOSS") -> 49
B10: Win Rate | C10: =IFERROR(COUNTIF('📓 Trade Journal'!AA3:AA52,"WIN")/(COUNTIF('📓 Trade Journal'!AA3:AA52,"WIN")+COUNTIF('📓 Trade Journal'!AA3:AA52,"LOSS")),0) -> 0
B11: Total Realised P&L | C11: =IFERROR(SUM('📓 Trade Journal'!Z3:Z52),0) -> 0
B12: Avg P&L per Trade | C12: =IFERROR(SUM('📓 Trade Journal'!Z3:Z52)/COUNTA('📓 Trade Journal'!Z3:Z52),0) -> 0
B13: Total Capital at Risk | C13: =IFERROR(SUM('📓 Trade Journal'!M3:M52),0) -> 545
B14: Avg Net Debit per Trade | C14: =IFERROR(AVERAGE('📓 Trade Journal'!K3:K52),0) -> 0.109
B15: Avg Return on Risk | C15: =IFERROR(AVERAGE('📓 Trade Journal'!W3:W52),0) -> 1.7522936
B16: PRICE Compliance Rate | C16: =IFERROR(COUNTIF('📓 Trade Journal'!S3:S52,5)/COUNTA('📓 Trade Journal'!S3:S52),0) -> 0.02
A18: 🏆 WIN / LOSS BREAKDOWN
B19: Metric | C19: WIN Trades | D19: LOSS Trades
B20: Count | C20: =COUNTIF('📓 Trade Journal'!AA3:AA52,"WIN") -> 0 | D20: =COUNTIF('📓 Trade Journal'!AA3:AA52,"LOSS") -> 49
B21: Total P&L | C21: =SUMIF('📓 Trade Journal'!AA3:AA52,"WIN",'📓 Trade Journal'!Z3:Z52) -> 0 | D21: =SUMIF('📓 Trade Journal'!AA3:AA52,"LOSS",'📓 Trade Journal'!Z3:Z52) -> 0
B22: Avg P&L | C22: =IFERROR(SUMIF('📓 Trade Journal'!AA3:AA52,"WIN",'📓 Trade Journal'!Z3:Z52)/COUNTIF('📓 Trade Journal'!AA3:AA52,"WIN"),0) -> 0 | D22: =IFERROR(SUMIF('📓 Trade Journal'!AA3:AA52,"LOSS",'📓 Trade Journal'!Z3:Z52)/COUNTIF('📓 Trade Journal'!AA3:AA52,"LOSS"),0) -> 0
B23: Avg R:R | C23: =IFERROR(AVERAGEIF('📓 Trade Journal'!AA3:AA52,"WIN",'📓 Trade Journal'!W3:W52),0) -> 0 | D23: =IFERROR(AVERAGEIF('📓 Trade Journal'!AA3:AA52,"LOSS",'📓 Trade Journal'!W3:W52),0) -> 0

Sheet 📚 PRICE Cheatsheet
A1: 📚 PRICE EXECUTION CHEATSHEET — Bull Call Spread Breakout Playbook
A4: ⚡ THE 5-STEP PRICE EXECUTION FRAMEWORK
B5: P | C5: PICK Expiration | D5: • Target 30–45 DTE (sweet spot) • Minimum: 8DTE × 2 = 16 DTE • Avoid earnings window ±7 days • Use EM column to reference expected move per expiry | E5: moomoo: Options Chain → Expiry dropdown → Check IV & EM column Select May 1 (22D) or later for standard setup
B9: R | C9: REVIEW Strike Price | D9: • Long call: ATM or slightly OTM • Delta 0.40–0.55 on long call • Short call: at resistance zone or EM upper bound • TSM example: Buy 340C / Sell 355C | E9: moomoo: Strategy Builder → Adjust long/short strikes Check that short strike is ABOVE your price target
B13: I | C13: INSPECT Liquidity | D13: • Bid-ask spread < $0.20 per leg • Open Interest > 100 contracts per leg • Volume ratio > 1.5× average • Tight spread = better fill at mid-price | E13: moomoo: Options Chain → Table view → Bid / Ask columns Filter: Both ITM & OTM, check for wide markets
B17: C | C17: CONDITION Check | D17: • EMA21 > EMA50 > EMA200 on daily chart • Price in upper 25% of 52-week range • IV Rank < 50 (low IV environment) • Analyst consensus: Buy / Strong Buy | E17: moomoo: Chart tab → Add EMA indicators Valuation tab → Analyst Ratings IV Analysis tab → Check IV Rank & Percentile
B21: E | C21: EXECUTE at Mid-Price | D21: • Place LIMIT order at mid-price • Never chase the ask • Set 50% take-profit GTC immediately on entry • Set exit alert at breakeven and short strike | E21: moomoo: Strategy Builder → Submit as Limit order Set GTC limit: close when spread = 70–80% of max value Set loss alert: close when debit drops 50%
A30: 🔑 ENTRY & EXIT TRIGGER TABLE
B31: Type | C31: Signal | D31: Action | E31: moomoo Tool
B32: ✅ ENTRY | C32: EMA21 > EMA50 > EMA200 daily | D32: Only enter if full EMA stack aligned | E32: Chart → EMA indicators
B33: ✅ ENTRY | C33: Fresh cross above EMA21 + volume | D33: Confirms momentum breakout | E33: Chart → Volume ratio > 1.5×
B34: ✅ ENTRY | C34: Near 52-week high / breakout level | D34: Price in upper 25% of 52-wk range | E34: Chart → 52-week high marker
B35: ✅ ENTRY | C35: IV Rank < 50% | D35: Low IV = cheaper spread premium | E35: Options → IV Analysis tab
B36: ✅ ENTRY | C36: PRICE score = 5/5 | D36: All 5 checklist boxes ticked | E36: Trade Journal → Column S
B37: 💰 EXIT WIN | C37: Spread reaches 70–80% of max profit | D37: Close entire spread for profit | E37: Strategy Builder → GTC limit
B38: 💰 EXIT WIN | C38: Price above short strike expiry | D38: Max profit achieved — close immediately | E38: Options Curve → Check P&L
B39: 🛑 EXIT LOSS | C39: Spread loses 50% of net debit | D39: Cut loss (e.g. debit $8.45 → close at $4.22) | E39: Strategy Builder → GTC stop
B40: 🛑 EXIT LOSS | C40: 2–3× red candle vs prior green | D40: Technical reversal signal — exit immediately | E40: Chart → Candle analysis
B41: 🛑 EXIT LOSS | C41: Close below prior day's low | D41: Institutional selling confirmed | E41: Chart → Daily close
B42: ⚠️ AVOID | C42: Earnings announcement ±7 days | D42: IV crush risk — do NOT hold through | E42: Options Chain → Earnings date
A45: 🔍 MOOMOO SCREENER QUICK FILTERS — 'Breakout Play' Preset
B46: Filter | C46: Value | D46: Filter | E46: Value
B47: Exchange | C47: NYSE / AMEX / Nasdaq | D47: Market Cap | E47: > $100B (Large Cap)
B48: Stock Price | C48: > $50 | D48: Volume Ratio | E48: > 1.5× (Intraday Turnover > 100K)
B49: EMA 21 | C49: Greater than EMA 50 | D49: EMA 50 | E49: Greater than EMA 200
B50: IV Percentile | C50: < 50% (ideal) | D50: Analyst Consensus | E50: Buy / Strong Buy
B51: Options Eligible | C51: Yes | D51: New High | E51: Today or within 5 days
